Metadata-Version: 1.1
Name: ofxparse
Version: 0.18
Summary: Tools for working with the OFX (Open Financial Exchange) file format
Home-page: http://sites.google.com/site/ofxparse
Author: Jerry Seutter
Author-email: jseutter.ofxparse@gmail.com
License: MIT License
Keywords: ofx,Open Financial Exchange,file formats
Platform: UNKNOWN
Classifier: Development Status :: 4 - Beta
Classifier: Intended Audience :: Developers
Classifier: Natural Language :: English
Classifier: Operating System :: OS Independent
Classifier: Programming Language :: Python :: 2.7
Classifier: Programming Language :: Python :: 3
Classifier: Programming Language :: Python :: 3.4
Classifier: Programming Language :: Python :: 3.5
Classifier: Programming Language :: Python :: 3.6
Classifier: Topic :: Software Development :: Libraries :: Python Modules
Classifier: Topic :: Utilities
Classifier: License :: OSI Approved :: MIT License
